[
  {
    "name": "シェフレラ",
    "interval": 9,
    "last_watered": "2026-06-28"
  },
  {
    "name": "パキラ",
    "interval": 4,
    "last_watered": "2026-07-03"
  },
  {
    "name": "スペアミント",
    "interval": 2,
    "last_watered": "2026-07-05"
  },
  {
    "name": "モヒートミント",
    "interval": 1.5,
    "last_watered": "2026-07-05"
  },
  {
    "name": "オレンジミント",
    "interval": 1.5,
    "last_watered": "2026-07-06"
  },
  {
    "name": "アジアンタム",
    "interval": 1,
    "last_watered": "2026-07-06"
  },
  {
    "name": "ミリオンバンブー",
    "interval": 3,
    "last_watered": "2026-07-04"
  },
  {
    "name": "カモミール",
    "interval": 2,
    "last_watered": "2026-07-06"
  },
  {
    "name": "シュガーパイン",
    "interval": 2,
    "last_watered": "2026-07-05"
  },
  {
    "name": "クワズイモ",
    "interval": 5,
    "last_watered": "2026-07-03"
  }
]